LICENSE.txt
setup.py
RPICommLink/__init__.py
RPICommLink.egg-info/PKG-INFO
RPICommLink.egg-info/SOURCES.txt
RPICommLink.egg-info/dependency_links.txt
RPICommLink.egg-info/top_level.txt