Metadata-Version: 2.1
Name: RPICommLink
Version: 1.1.3
Summary: A library for communication on Raspberry Pi
Author: adixu
Author-email: adixu7@gmail.com
License-File: LICENSE.txt
